pioverifier/__init__.py
pioverifier-0.1.0.dist-info/LICENSE
pioverifier-0.1.0.dist-info/METADATA
pioverifier-0.1.0.dist-info/WHEEL
pioverifier-0.1.0.dist-info/top_level.txt
pioverifier-0.1.0.dist-info/RECORD
