Metadata-Version: 2.1
Name: pioverifier
Version: 0.1.0
Summary: A simple CLI tool to verify platformio.ini file
Home-page: https://github.com/dakalamin/pioverifier
Author: Daniil Kalamin
Author-email: dakalamin@gmail.com
License: MIT
Keywords: CLI,embedded,pio,platformio,verification
Classifier: Development Status :: 1 - Planning
Classifier: Environment :: Console
Classifier: Intended Audience :: Developers
Classifier: License :: OSI Approved :: MIT License
Classifier: Operating System :: OS Independent
Classifier: Programming Language :: Python
Classifier: Programming Language :: Python :: 3
Classifier: Programming Language :: Python :: 3 :: Only
Classifier: Programming Language :: Python :: 3.11
Classifier: Topic :: Software Development :: Libraries :: Python Modules
Classifier: Topic :: Software Development :: Embedded Systems
Classifier: Topic :: Utilities
Classifier: Typing :: Typed
Requires-Python: >=3.11
License-File: LICENSE
Requires-Dist: click
Requires-Dist: platformio
Provides-Extra: dev
Requires-Dist: build ; extra == 'dev'
Requires-Dist: twine ; extra == 'dev'
